MANIFEST.in
README.md
co2mco.c
command_composite.c
command_dist.c
command_dist_wrapper.c
command_set.c
command_shuffle.c
global_basic.c
iseq2comem.c
kssdutils.py
mman.c
mytime.c
pykssd.c
setup.py
kssdheaders/co2mco.h
kssdheaders/command_composite.h
kssdheaders/command_dist.h
kssdheaders/command_dist_wrapper.h
kssdheaders/command_set.h
kssdheaders/command_shuffle.h
kssdheaders/global_basic.h
kssdheaders/iseq2comem.h
kssdheaders/mman.h
kssdheaders/mytime.h
kssdutils.egg-info/PKG-INFO
kssdutils.egg-info/SOURCES.txt
kssdutils.egg-info/dependency_links.txt
kssdutils.egg-info/not-zip-safe
kssdutils.egg-info/requires.txt
kssdutils.egg-info/top_level.txt