Metadata-Version: 2.1
Name: kssdutils
Version: 1.1.0
Summary: kssdutils is a Python package for genome analysis, such as sketch, dist.
Home-page: UNKNOWN
Author: Hang Yang
Author-email: yhlink1207@gmail.com
License: UNKNOWN
Platform: UNKNOWN
